pyLIMA/__init__.py
pyLIMA/event.py
pyLIMA/telescopes.py
pyLIMA/astrometry/__init__.py
pyLIMA/astrometry/astrometric_positions.py
pyLIMA/astrometry/astrometric_shifts.py
pyLIMA/caustics/__init__.py
pyLIMA/caustics/binary_caustics.py
pyLIMA/data/Bressan_Isochrones.dat
pyLIMA/data/Bressan_Isochrones_old.dat
pyLIMA/data/Claret2011.fits
pyLIMA/data/Roman_Filters.dat
pyLIMA/data/Yoo_B0B1.dat
pyLIMA/data/__init__.py
pyLIMA/fits/BOOTSTRAP_fit.py
pyLIMA/fits/DEMC_fit.py
pyLIMA/fits/DE_fit.py
pyLIMA/fits/DREAM_fit.py
pyLIMA/fits/GRIDS_fit.py
pyLIMA/fits/LM_fit.py
pyLIMA/fits/MCMC_fit.py
pyLIMA/fits/MINIMIZE_fit.py
pyLIMA/fits/MINUIT_fit.py
pyLIMA/fits/ML_fit.py
pyLIMA/fits/NGSA2_fit.py
pyLIMA/fits/TRF_fit.py
pyLIMA/fits/__init__.py
pyLIMA/fits/fit_metrics.py
pyLIMA/fits/objective_functions.py
pyLIMA/fits/stats.py
pyLIMA/magnification/__init__.py
pyLIMA/magnification/impact_parameter.py
pyLIMA/magnification/magnification_FSPL.py
pyLIMA/magnification/magnification_Jacobian.py
pyLIMA/magnification/magnification_PSPL.py
pyLIMA/magnification/magnification_VBB.py
pyLIMA/models/FSBL_model.py
pyLIMA/models/FSPL_model.py
pyLIMA/models/FSPLarge_model.py
pyLIMA/models/ML_model.py
pyLIMA/models/PSBL_model.py
pyLIMA/models/PSPL_model.py
pyLIMA/models/USBL_model.py
pyLIMA/models/__init__.py
pyLIMA/models/generate_model.py
pyLIMA/models/pyLIMA_fancy_parameters.py
pyLIMA/orbitalmotion/__init__.py
pyLIMA/orbitalmotion/orbital_motion.py
pyLIMA/orbitalmotion/orbital_motion_2D.py
pyLIMA/orbitalmotion/orbital_motion_3D.py
pyLIMA/outputs/__init__.py
pyLIMA/outputs/file_outputs.py
pyLIMA/outputs/pyLIMA_plots.py
pyLIMA/parallax/JPL_ephemerides.py
pyLIMA/parallax/__init__.py
pyLIMA/parallax/astropy_ephemerides.py
pyLIMA/parallax/parallax.py
pyLIMA/priors/__init__.py
pyLIMA/priors/guess.py
pyLIMA/priors/parameters_boundaries.py
pyLIMA/priors/parameters_priors.py
pyLIMA/pyLIMASS/__init__.py
pyLIMA/pyLIMASS/pyLIMASS.py
pyLIMA/simulations/__init__.py
pyLIMA/simulations/simulator.py
pylima-1.9.8.dist-info/licenses/LICENSE
pylima-1.9.8.dist-info/METADATA
pylima-1.9.8.dist-info/WHEEL
pylima-1.9.8.dist-info/top_level.txt
pylima-1.9.8.dist-info/RECORD
