Metadata-Version: 2.4
Name: pyLIMA
Version: 1.9.8
Summary: Microlsening analysis package.
Author-email: Etienne Bachelet <etibachelet@gmail.com>
License-Expression: GPL-3.0-or-later
Project-URL: Homepage, http://github.com/ebachelet/pyLIMA
Project-URL: Documentation, https://pylima.readthedocs.io/en/latest/
Keywords: Microlsening analysis package
Classifier: Development Status :: 5 - Production/Stable
Classifier: Intended Audience :: Developers
Classifier: Topic :: Software Development :: Build Tools
Classifier: Programming Language :: Python :: 3
Requires-Python: <4,>=3.6
License-File: LICENSE
Requires-Dist: astropy
Requires-Dist: astroquery
Requires-Dist: bokeh
Requires-Dist: emcee
Requires-Dist: importlib-metadata
Requires-Dist: kepler.py
Requires-Dist: numpy>=1.7
Requires-Dist: pygtc
Requires-Dist: pymoo
Requires-Dist: scipy>=1.0
Requires-Dist: tqdm>=4.0
Requires-Dist: VBMicrolensing
Requires-Dist: speclite
Requires-Dist: scikit-learn
Requires-Dist: importlib-resources; python_version < "3.9"
Requires-Dist: iminuit
Dynamic: license-file
